[{"event_id":13808,"event_start_unix":"2021-01-11T07:30:00.000Z","event_end_unix":"2021-01-11T08:30:00.000Z","event_title":"TheVR Happy Hour #858 - 01.11.","event_image":"https://thevr.hu/wp-content/uploads/2021/01/1.0-YT-size.jpg","event_description":"\n\t\t\t\t\t\t\t\t\t\t<p><!-- wp:paragraph --></p>\n<p>TheVR Happy Hour #858 &#8211; 01.11.</p>\n<p><!-- /wp:paragraph --></p>\n","event_repeat_interval":"0"},{"event_id":13813,"event_start_unix":"2021-01-11T12:00:00.000Z","event_end_unix":"2021-01-11T16:30:00.000Z","event_title":"Star Wars: The Force Unleashed II","event_image":"https://thevr.hu/wp-content/uploads/2021/01/SWTFU2.jpg","event_description":"\n\t\t\t\t\t\t\t\t\t\t<p><!-- wp:paragraph --></p>\n<p>Star Wars: The Force Unleashed II</p>\n<p><!-- /wp:paragraph --></p>\n","event_repeat_interval":"0"},{"event_id":13809,"event_start_unix":"2021-01-12T07:30:00.000Z","event_end_unix":"2021-01-12T08:30:00.000Z","event_title":"TheVR Happy Hour #859 - 01.12.","event_image":"https://thevr.hu/wp-content/uploads/2021/01/1.0-YT-size.jpg","event_description":"\n\t\t\t\t\t\t\t\t\t\t<p><!-- wp:paragraph --></p>\n<p>TheVR Happy Hour #859 &#8211; 01.12.</p>\n<p><!-- /wp:paragraph --></p>\n","event_repeat_interval":"0"},{"event_id":13815,"event_start_unix":"2021-01-12T12:00:00.000Z","event_end_unix":"2021-01-12T16:30:00.000Z","event_title":"Deus Ex: Human Revolution","event_image":"https://thevr.hu/wp-content/uploads/2021/01/deusexHR.jpg","event_description":"\n\t\t\t\t\t\t\t\t\t\t<p><!-- wp:paragraph --></p>\n<p>Deus Ex: Human Revolution</p>\n<p><!-- /wp:paragraph --></p>\n","event_repeat_interval":"0"},{"event_id":13810,"event_start_unix":"2021-01-13T07:30:00.000Z","event_end_unix":"2021-01-13T08:30:00.000Z","event_title":"TheVR Happy Hour #860 - 01.13.","event_image":"https://thevr.hu/wp-content/uploads/2021/01/1.0-YT-size.jpg","event_description":"\n\t\t\t\t\t\t\t\t\t\t<p><!-- wp:paragraph --></p>\n<p>TheVR Happy Hour #859 &#8211; 01.12.</p>\n<p><!-- /wp:paragraph --></p>\n","event_repeat_interval":"0"},{"event_id":13816,"event_start_unix":"2021-01-13T12:00:00.000Z","event_end_unix":"2021-01-13T16:30:00.000Z","event_title":"Prototype","event_image":"https://thevr.hu/wp-content/uploads/2021/01/prototype.jpg","event_description":"\n\t\t\t\t\t\t\t\t\t\t<p><!-- wp:paragraph --></p>\n<p>Prototype</p>\n<p><!-- /wp:paragraph --></p>\n","event_repeat_interval":"0"},{"event_id":13811,"event_start_unix":"2021-01-14T07:30:00.000Z","event_end_unix":"2021-01-14T08:30:00.000Z","event_title":"TheVR Happy Hour #861 - 01.14.","event_image":"https://thevr.hu/wp-content/uploads/2021/01/1.0-YT-size.jpg","event_description":"\n\t\t\t\t\t\t\t\t\t\t<p><!-- wp:paragraph --></p>\n<p>TheVR Happy Hour #861 &#8211; 01.14.</p>\n<p><!-- /wp:paragraph --></p>\n","event_repeat_interval":"0"},{"event_id":13818,"event_start_unix":"2021-01-14T12:00:00.000Z","event_end_unix":"2021-01-14T16:30:00.000Z","event_title":"Star Wars: The Force Unleashed II","event_image":"https://thevr.hu/wp-content/uploads/2021/01/SWTFU2.jpg","event_description":"\n\t\t\t\t\t\t\t\t\t\t<p><!-- wp:paragraph --></p>\n<p>Star Wars: The Force Unleashed II</p>\n<p><!-- /wp:paragraph --></p>\n","event_repeat_interval":"0"},{"event_id":13812,"event_start_unix":"2021-01-15T07:30:00.000Z","event_end_unix":"2021-01-15T08:30:00.000Z","event_title":"TheVR Happy Hour #862 - 01.15.","event_image":"https://thevr.hu/wp-content/uploads/2021/01/1.0-YT-size.jpg","event_description":"\n\t\t\t\t\t\t\t\t\t\t<p><!-- wp:paragraph --></p>\n<p>TheVR Happy Hour #862 &#8211; 01.15.</p>\n<p><!-- /wp:paragraph --></p>\n","event_repeat_interval":"0"},{"event_id":13819,"event_start_unix":"2021-01-15T12:00:00.000Z","event_end_unix":"2021-01-15T16:30:00.000Z","event_title":"Deus Ex: Human Revolution","event_image":"https://thevr.hu/wp-content/uploads/2021/01/deusexHR.jpg","event_description":"\n\t\t\t\t\t\t\t\t\t\t<p><!-- wp:paragraph --></p>\n<p>Deus Ex: Human Revolution</p>\n<p><!-- /wp:paragraph --></p>\n","event_repeat_interval":"0"}]