[{"event_id":1615,"event_start_unix":"2020-06-04T06:30:00.000Z","event_end_unix":"2020-06-04T07:30:00.000Z","event_title":"TheVR Happy Hour #721 – 06.04.","event_image":"https://thevr.hu/wp-content/uploads/2019/11/1.0-YT-size.jpg","event_description":"TheVR Happy Hour #720 – 06.03.","event_repeat_interval":"0"},{"event_id":1768,"event_start_unix":"2020-06-04T12:00:00.000Z","event_end_unix":"2020-06-04T15:30:00.000Z","event_title":"COD: Modern Warfare - Hard Mode","event_image":"https://thevr.hu/wp-content/uploads/2020/01/cod.mw_.hard_.mode_.logo_.jpg","event_description":"COD: Modern Warfare - Hard Mode","event_repeat_interval":"0"},{"event_id":1918,"event_start_unix":"2020-06-04T16:30:00.000Z","event_end_unix":"2020-06-04T17:30:00.000Z","event_title":"Those Who Remain - Befejezés","event_image":"https://thevr.hu/wp-content/uploads/2020/05/banner_1600x800.jpg","event_description":"Those Who Remain - Befejezés","event_repeat_interval":"0"},{"event_id":1906,"event_start_unix":"2020-06-04T17:30:00.000Z","event_end_unix":"2020-06-04T19:30:00.000Z","event_title":"VALORANT - Lássuk, milyen lett a végleges változat...","event_image":"https://thevr.hu/wp-content/uploads/2020/04/cover.0-1.jpg","event_description":"VALORANT - Lássuk, milyen lett a végleges változat...","event_repeat_interval":"0"},{"event_id":1616,"event_start_unix":"2020-06-05T06:30:00.000Z","event_end_unix":"2020-06-05T07:30:00.000Z","event_title":"TheVR Happy Hour #722 – 06.05.","event_image":"https://thevr.hu/wp-content/uploads/2019/11/1.0-YT-size.jpg","event_description":"TheVR Happy Hour #720 – 06.03.","event_repeat_interval":"0"},{"event_id":1898,"event_start_unix":"2020-06-05T12:00:00.000Z","event_end_unix":"2020-06-05T15:30:00.000Z","event_title":"Maneater - Befejezés | Mafia II Remastered - Befejezés","event_image":"https://thevr.hu/wp-content/uploads/2020/05/maneater.maffia.jpg","event_description":"Maneater - Befejezés | Mafia II Remastered - Befejezés","event_repeat_interval":"0"}]