[{"event_id":2177,"event_start_unix":"2020-10-15T06:30:00.000Z","event_end_unix":"2020-10-15T07:30:00.000Z","event_title":"TheVR Happy Hour #809 – 10.15.","event_image":"https://thevr.hu/wp-content/uploads/2019/11/1.0-YT-size.jpg","event_description":"TheVR Happy Hour #809 – 10.15.","event_repeat_interval":"0"},{"event_id":2190,"event_start_unix":"2020-10-15T11:00:00.000Z","event_end_unix":"2020-10-15T13:00:00.000Z","event_title":"Dark Souls II: Scholar of the First Sin | Folytatás","event_image":"https://thevr.hu/wp-content/uploads/2020/10/ds2-1418310781.jpg","event_description":"Dark Souls III: Scholar of the First Sin | Folytatás","event_repeat_interval":"0"},{"event_id":2200,"event_start_unix":"2020-10-15T13:00:00.000Z","event_end_unix":"2020-10-15T15:30:00.000Z","event_title":"Phasmophobia","event_image":"https://thevr.hu/wp-content/uploads/2020/10/phasmaphobia.jpg","event_description":"<!-- wp:paragraph --> <p>Multihorror? :D</p> <!-- /wp:paragraph -->","event_repeat_interval":"0"},{"event_id":2139,"event_start_unix":"2020-10-16T06:30:00.000Z","event_end_unix":"2020-10-16T07:30:00.000Z","event_title":"TheVR Happy Hour #810 – 10.16.","event_image":"https://thevr.hu/wp-content/uploads/2019/11/1.0-YT-size.jpg","event_description":"TheVR Happy Hour #810 – 10.16.","event_repeat_interval":"0"},{"event_id":2198,"event_start_unix":"2020-10-16T11:00:00.000Z","event_end_unix":"2020-10-16T14:00:00.000Z","event_title":"CALL OF DUTY: BLACK OPS CW BETA","event_image":"https://thevr.hu/wp-content/uploads/2020/10/codbocw.jpg","event_description":"<!-- wp:paragraph --> <p>CALL OF DUTY: BLACK OPS CW BETA</p> <!-- /wp:paragraph -->","event_repeat_interval":"0"}]