[{"event_id":"652560","event_start_unix":"2019-12-18T18:00:00.000Z","event_end_unix":"2019-12-18T22:30:00.000Z","event_title":"ESTI STREAM","event_image":"","event_description":""},{"event_id":"634360","event_start_unix":"2019-12-22T11:00:00.000Z","event_end_unix":"2019-12-22T18:00:00.000Z","event_title":"800 FŐS DUO VERSENY - BLYYYCUP","event_image":"https://static.wixstatic.com/media/de36f2_a802c125f7f544d4abb9047189d24a59~mv2.png","event_description":""},{"event_id":"642001","event_start_unix":"2019-12-22T23:00:00.000Z","event_end_unix":"2019-12-27T23:00:00.000Z","event_title":"- SZÜNET - BOLDOG KARÁCSONYT <3","event_image":"https://static.wixstatic.com/media/de36f2_ec036cf7fece4e0aa1a757b8e99b75f9~mv2.jpg","event_description":""}]