[{"event_start_unix":"2020-06-13T14:30:00.000Z","event_end_unix":"2020-06-13T20:00:00.000Z","event_title":"CHILLES VALORANT","event_image":"","event_description":""},{"event_start_unix":"2020-06-14T17:00:00.000Z","event_end_unix":"2020-06-14T21:00:00.000Z","event_title":"BÁRMI IS LEHET","event_image":"","event_description":""},{"event_start_unix":"2020-06-16T16:00:00.000Z","event_end_unix":"2020-06-16T20:00:00.000Z","event_title":"ÚJRA ITT!","event_image":"","event_description":""},{"event_start_unix":"2020-06-24T08:00:00.000Z","event_end_unix":"2020-06-24T12:00:00.000Z","event_title":"TWITCH RIVALS: COD WARZONE SHOWDOWN w/ LegoTroopR + TheVR Jani","event_image":"","event_description":""}]