[{"event_id":"667146","event_start_unix":"2020-01-02T16:00:00.000Z","event_end_unix":"2020-01-02T21:00:00.000Z","event_title":"2020 ELSŐ STREAMJE","event_image":"https://static.wixstatic.com/media/de36f2_5b5b2e9ea7324c8ea08f900d483f8a36~mv2_d_1890_2268_s_2.jpg","event_description":""},{"event_id":"667260","event_start_unix":"2020-01-03T09:00:00.000Z","event_end_unix":"2020-01-03T15:00:00.000Z","event_title":"STAR WARS FOLYTATÁS #3","event_image":"https://static.wixstatic.com/media/de36f2_fa4ff5d610f14e85bee27bb40af07cab~mv2.jpg","event_description":""}]